basicDemoLib/__init__.py
basicDemoLib-0.1.dist-info/LICENSE
basicDemoLib-0.1.dist-info/METADATA
basicDemoLib-0.1.dist-info/WHEEL
basicDemoLib-0.1.dist-info/top_level.txt
basicDemoLib-0.1.dist-info/RECORD
