Metadata-Version: 2.1
Name: basicDemoLib
Version: 0.1
Summary: Small library for basic calculator functions
Home-page: UNKNOWN
Author: Venkat
Author-email: venkatin2sl@gmail.com
License: UNKNOWN
Platform: UNKNOWN
Classifier: Programming Language :: Python :: 3
Classifier: License :: OSI Approved :: MIT License
Classifier: Operating System :: OS Independent
License-File: LICENSE
